{
  "deck": "Flashit - ccna-show-command-reflexes.apkg",
  "count": 106,
  "cards": [
    {
      "front": "Which show \u2014 \"is this prefix in the routing table?\"",
      "back": "`show ip route` (filter: `show ip route 10.1.1.0`)",
      "tags": "flashcards/ccna-show-command-reflexes"
    },
    {
      "front": "`show ip route` (filter: `show ip route 10.1.1.0`)",
      "back": "Which show \u2014 \"is this prefix in the routing table?\"",
      "tags": "flashcards/ccna-show-command-reflexes"
    },
    {
      "front": "Which show \u2014 \"what AD/metric is the route using?\"",
      "back": "`show ip route X.X.X.X` \u2014 output shows AD/metric in brackets",
      "tags": "flashcards/ccna-show-command-reflexes"
    },
    {
      "front": "`show ip route X.X.X.X` \u2014 output shows AD/metric in brackets",
      "back": "Which show \u2014 \"what AD/metric is the route using?\"",
      "tags": "flashcards/ccna-show-command-reflexes"
    },
    {
      "front": "Which show \u2014 \"what's currently configured on this device?\"",
      "back": "`show running-config` (or `show run | section X` to filter)",
      "tags": "flashcards/ccna-show-command-reflexes"
    },
    {
      "front": "`show running-config` (or `show run | section X` to filter)",
      "back": "Which show \u2014 \"what's currently configured on this device?\"",
      "tags": "flashcards/ccna-show-command-reflexes"
    },
    {
      "front": "Which show \u2014 \"what config will load on next boot?\"",
      "back": "`show startup-config`",
      "tags": "flashcards/ccna-show-command-reflexes"
    },
    {
      "front": "`show startup-config`",
      "back": "Which show \u2014 \"what config will load on next boot?\"",
      "tags": "flashcards/ccna-show-command-reflexes"
    },
    {
      "front": "Which show \u2014 \"is the interface up/down?\"",
      "back": "`show ip interface brief` (one-line per interface \u2014 status + protocol + IP)",
      "tags": "flashcards/ccna-show-command-reflexes"
    },
    {
      "front": "`show ip interface brief` (one-line per interface \u2014 status + protocol + IP)",
      "back": "Which show \u2014 \"is the interface up/down?\"",
      "tags": "flashcards/ccna-show-command-reflexes"
    },
    {
      "front": "Which show \u2014 \"physical layer errors, duplex, speed?\"",
      "back": "`show interfaces gX/Y` (full counters: CRC, input errors, collisions)",
      "tags": "flashcards/ccna-show-command-reflexes"
    },
    {
      "front": "`show interfaces gX/Y` (full counters: CRC, input errors, collisions)",
      "back": "Which show \u2014 \"physical layer errors, duplex, speed?\"",
      "tags": "flashcards/ccna-show-command-reflexes"
    },
    {
      "front": "Which show \u2014 \"what speed/duplex did the port negotiate?\"",
      "back": "`show interfaces gX/Y` or `show interfaces status` (on switch)",
      "tags": "flashcards/ccna-show-command-reflexes"
    },
    {
      "front": "`show interfaces gX/Y` or `show interfaces status` (on switch)",
      "back": "Which show \u2014 \"what speed/duplex did the port negotiate?\"",
      "tags": "flashcards/ccna-show-command-reflexes"
    },
    {
      "front": "Which show \u2014 \"switch port status overview?\"",
      "back": "`show interfaces status` (one line per port \u2014 vlan, duplex, speed, type)",
      "tags": "flashcards/ccna-show-command-reflexes"
    },
    {
      "front": "`show interfaces status` (one line per port \u2014 vlan, duplex, speed, type)",
      "back": "Which show \u2014 \"switch port status overview?\"",
      "tags": "flashcards/ccna-show-command-reflexes"
    },
    {
      "front": "Which show \u2014 \"what VLAN is the port in?\"",
      "back": "`show vlan brief` (port-to-VLAN mapping)",
      "tags": "flashcards/ccna-show-command-reflexes"
    },
    {
      "front": "`show vlan brief` (port-to-VLAN mapping)",
      "back": "Which show \u2014 \"what VLAN is the port in?\"",
      "tags": "flashcards/ccna-show-command-reflexes"
    },
    {
      "front": "Which show \u2014 \"switchport mode + trunk details?\"",
      "back": "`show interfaces gX/Y switchport`",
      "tags": "flashcards/ccna-show-command-reflexes"
    },
    {
      "front": "`show interfaces gX/Y switchport`",
      "back": "Which show \u2014 \"switchport mode + trunk details?\"",
      "tags": "flashcards/ccna-show-command-reflexes"
    },
    {
      "front": "Which show \u2014 \"what VLANs does this trunk carry?\"",
      "back": "`show interfaces trunk` (also shows native VLAN + encapsulation)",
      "tags": "flashcards/ccna-show-command-reflexes"
    },
    {
      "front": "`show interfaces trunk` (also shows native VLAN + encapsulation)",
      "back": "Which show \u2014 \"what VLANs does this trunk carry?\"",
      "tags": "flashcards/ccna-show-command-reflexes"
    },
    {
      "front": "Which show \u2014 \"what's the trunk's native VLAN?\"",
      "back": "`show interfaces trunk` \u2014 column \"Native vlan\"",
      "tags": "flashcards/ccna-show-command-reflexes"
    },
    {
      "front": "`show interfaces trunk` \u2014 column \"Native vlan\"",
      "back": "Which show \u2014 \"what's the trunk's native VLAN?\"",
      "tags": "flashcards/ccna-show-command-reflexes"
    },
    {
      "front": "Which show \u2014 \"are OSPF neighbors up + in Full state?\"",
      "back": "`show ip ospf neighbor`",
      "tags": "flashcards/ccna-show-command-reflexes"
    },
    {
      "front": "`show ip ospf neighbor`",
      "back": "Which show \u2014 \"are OSPF neighbors up + in Full state?\"",
      "tags": "flashcards/ccna-show-command-reflexes"
    },
    {
      "front": "Which show \u2014 \"is this router the DR/BDR?\"",
      "back": "`show ip ospf neighbor` \u2014 state column shows FULL/DR or FULL/BDR",
      "tags": "flashcards/ccna-show-command-reflexes"
    },
    {
      "front": "`show ip ospf neighbor` \u2014 state column shows FULL/DR or FULL/BDR",
      "back": "Which show \u2014 \"is this router the DR/BDR?\"",
      "tags": "flashcards/ccna-show-command-reflexes"
    },
    {
      "front": "Which show \u2014 \"OSPF router-id + area + cost per interface?\"",
      "back": "`show ip ospf interface` (or `show ip ospf interface brief`)",
      "tags": "flashcards/ccna-show-command-reflexes"
    },
    {
      "front": "`show ip ospf interface` (or `show ip ospf interface brief`)",
      "back": "Which show \u2014 \"OSPF router-id + area + cost per interface?\"",
      "tags": "flashcards/ccna-show-command-reflexes"
    },
    {
      "front": "Which show \u2014 \"OSPF LSDB contents?\"",
      "back": "`show ip ospf database`",
      "tags": "flashcards/ccna-show-command-reflexes"
    },
    {
      "front": "`show ip ospf database`",
      "back": "Which show \u2014 \"OSPF LSDB contents?\"",
      "tags": "flashcards/ccna-show-command-reflexes"
    },
    {
      "front": "Which show \u2014 \"what routing protocols are running on this router?\"",
      "back": "`show ip protocols`",
      "tags": "flashcards/ccna-show-command-reflexes"
    },
    {
      "front": "`show ip protocols`",
      "back": "Which show \u2014 \"what routing protocols are running on this router?\"",
      "tags": "flashcards/ccna-show-command-reflexes"
    },
    {
      "front": "Which show \u2014 \"passive interfaces under OSPF?\"",
      "back": "`show ip protocols` (lists passive interfaces section)",
      "tags": "flashcards/ccna-show-command-reflexes"
    },
    {
      "front": "`show ip protocols` (lists passive interfaces section)",
      "back": "Which show \u2014 \"passive interfaces under OSPF?\"",
      "tags": "flashcards/ccna-show-command-reflexes"
    },
    {
      "front": "Which show \u2014 \"directly connected Cisco neighbors?\"",
      "back": "`show cdp neighbors`",
      "tags": "flashcards/ccna-show-command-reflexes"
    },
    {
      "front": "`show cdp neighbors`",
      "back": "Which show \u2014 \"directly connected Cisco neighbors?\"",
      "tags": "flashcards/ccna-show-command-reflexes"
    },
    {
      "front": "Which show \u2014 \"neighbor's IP + IOS version + platform?\"",
      "back": "`show cdp neighbors detail`",
      "tags": "flashcards/ccna-show-command-reflexes"
    },
    {
      "front": "`show cdp neighbors detail`",
      "back": "Which show \u2014 \"neighbor's IP + IOS version + platform?\"",
      "tags": "flashcards/ccna-show-command-reflexes"
    },
    {
      "front": "Which show \u2014 \"vendor-neutral neighbor discovery?\"",
      "back": "`show lldp neighbors`",
      "tags": "flashcards/ccna-show-command-reflexes"
    },
    {
      "front": "`show lldp neighbors`",
      "back": "Which show \u2014 \"vendor-neutral neighbor discovery?\"",
      "tags": "flashcards/ccna-show-command-reflexes"
    },
    {
      "front": "Which show \u2014 \"MAC address learned on which port?\"",
      "back": "`show mac address-table` (or `show mac address-table address XXXX.XXXX.XXXX`)",
      "tags": "flashcards/ccna-show-command-reflexes"
    },
    {
      "front": "`show mac address-table` (or `show mac address-table address XXXX.XXXX.XXXX`)",
      "back": "Which show \u2014 \"MAC address learned on which port?\"",
      "tags": "flashcards/ccna-show-command-reflexes"
    },
    {
      "front": "Which show \u2014 \"ARP cache / IP-to-MAC bindings?\"",
      "back": "`show ip arp` (or `show arp`)",
      "tags": "flashcards/ccna-show-command-reflexes"
    },
    {
      "front": "`show ip arp` (or `show arp`)",
      "back": "Which show \u2014 \"ARP cache / IP-to-MAC bindings?\"",
      "tags": "flashcards/ccna-show-command-reflexes"
    },
    {
      "front": "Which show \u2014 \"STP root bridge, port states, blocking ports?\"",
      "back": "`show spanning-tree` (per-VLAN view)",
      "tags": "flashcards/ccna-show-command-reflexes"
    },
    {
      "front": "`show spanning-tree` (per-VLAN view)",
      "back": "Which show \u2014 \"STP root bridge, port states, blocking ports?\"",
      "tags": "flashcards/ccna-show-command-reflexes"
    },
    {
      "front": "Which show \u2014 \"who is root bridge for VLAN 10?\"",
      "back": "`show spanning-tree vlan 10` (look for \"This bridge is the root\" or root MAC)",
      "tags": "flashcards/ccna-show-command-reflexes"
    },
    {
      "front": "`show spanning-tree vlan 10` (look for \"This bridge is the root\" or root MAC)",
      "back": "Which show \u2014 \"who is root bridge for VLAN 10?\"",
      "tags": "flashcards/ccna-show-command-reflexes"
    },
    {
      "front": "Which show \u2014 \"ACL line hits + matches?\"",
      "back": "`show access-lists` or `show ip access-lists`",
      "tags": "flashcards/ccna-show-command-reflexes"
    },
    {
      "front": "`show access-lists` or `show ip access-lists`",
      "back": "Which show \u2014 \"ACL line hits + matches?\"",
      "tags": "flashcards/ccna-show-command-reflexes"
    },
    {
      "front": "Which show \u2014 \"ACL applied on which interface, which direction?\"",
      "back": "`show ip interface gX/Y` \u2014 look for \"Outgoing access list\" + \"Inbound access list\"",
      "tags": "flashcards/ccna-show-command-reflexes"
    },
    {
      "front": "`show ip interface gX/Y` \u2014 look for \"Outgoing access list\" + \"Inbound access list\"",
      "back": "Which show \u2014 \"ACL applied on which interface, which direction?\"",
      "tags": "flashcards/ccna-show-command-reflexes"
    },
    {
      "front": "Which show \u2014 \"NAT translation table (current sessions)?\"",
      "back": "`show ip nat translations`",
      "tags": "flashcards/ccna-show-command-reflexes"
    },
    {
      "front": "`show ip nat translations`",
      "back": "Which show \u2014 \"NAT translation table (current sessions)?\"",
      "tags": "flashcards/ccna-show-command-reflexes"
    },
    {
      "front": "Which show \u2014 \"NAT total translations + hits?\"",
      "back": "`show ip nat statistics`",
      "tags": "flashcards/ccna-show-command-reflexes"
    },
    {
      "front": "`show ip nat statistics`",
      "back": "Which show \u2014 \"NAT total translations + hits?\"",
      "tags": "flashcards/ccna-show-command-reflexes"
    },
    {
      "front": "Which show \u2014 \"EtherChannel bundle state (LACP up?)?\"",
      "back": "`show etherchannel summary`",
      "tags": "flashcards/ccna-show-command-reflexes"
    },
    {
      "front": "`show etherchannel summary`",
      "back": "Which show \u2014 \"EtherChannel bundle state (LACP up?)?\"",
      "tags": "flashcards/ccna-show-command-reflexes"
    },
    {
      "front": "Which show \u2014 \"DHCP leases / who got what IP?\"",
      "back": "`show ip dhcp binding`",
      "tags": "flashcards/ccna-show-command-reflexes"
    },
    {
      "front": "`show ip dhcp binding`",
      "back": "Which show \u2014 \"DHCP leases / who got what IP?\"",
      "tags": "flashcards/ccna-show-command-reflexes"
    },
    {
      "front": "Which show \u2014 \"DHCP pool config + exclusions?\"",
      "back": "`show ip dhcp pool`",
      "tags": "flashcards/ccna-show-command-reflexes"
    },
    {
      "front": "`show ip dhcp pool`",
      "back": "Which show \u2014 \"DHCP pool config + exclusions?\"",
      "tags": "flashcards/ccna-show-command-reflexes"
    },
    {
      "front": "Which show \u2014 \"HSRP active/standby state?\"",
      "back": "`show standby brief`",
      "tags": "flashcards/ccna-show-command-reflexes"
    },
    {
      "front": "`show standby brief`",
      "back": "Which show \u2014 \"HSRP active/standby state?\"",
      "tags": "flashcards/ccna-show-command-reflexes"
    },
    {
      "front": "Which show \u2014 \"port-security violation count / sticky MACs?\"",
      "back": "`show port-security interface gX/Y`",
      "tags": "flashcards/ccna-show-command-reflexes"
    },
    {
      "front": "`show port-security interface gX/Y`",
      "back": "Which show \u2014 \"port-security violation count / sticky MACs?\"",
      "tags": "flashcards/ccna-show-command-reflexes"
    },
    {
      "front": "Which show \u2014 \"active SSH/Telnet sessions to this device?\"",
      "back": "`show users`",
      "tags": "flashcards/ccna-show-command-reflexes"
    },
    {
      "front": "`show users`",
      "back": "Which show \u2014 \"active SSH/Telnet sessions to this device?\"",
      "tags": "flashcards/ccna-show-command-reflexes"
    },
    {
      "front": "Which show \u2014 \"is SSH enabled and on what version?\"",
      "back": "`show ip ssh`",
      "tags": "flashcards/ccna-show-command-reflexes"
    },
    {
      "front": "`show ip ssh`",
      "back": "Which show \u2014 \"is SSH enabled and on what version?\"",
      "tags": "flashcards/ccna-show-command-reflexes"
    },
    {
      "front": "Which show \u2014 \"recent syslog messages on the device?\"",
      "back": "`show logging`",
      "tags": "flashcards/ccna-show-command-reflexes"
    },
    {
      "front": "`show logging`",
      "back": "Which show \u2014 \"recent syslog messages on the device?\"",
      "tags": "flashcards/ccna-show-command-reflexes"
    },
    {
      "front": "Which show \u2014 \"IOS version + uptime + serial?\"",
      "back": "`show version`",
      "tags": "flashcards/ccna-show-command-reflexes"
    },
    {
      "front": "`show version`",
      "back": "Which show \u2014 \"IOS version + uptime + serial?\"",
      "tags": "flashcards/ccna-show-command-reflexes"
    },
    {
      "front": "Sub-Q \"verify connectivity end-to-end\" \u2014 commands?",
      "back": "`ping X.X.X.X` then `traceroute X.X.X.X` (ping = reachable, traceroute = path)",
      "tags": "flashcards/ccna-show-command-reflexes"
    },
    {
      "front": "`ping X.X.X.X` then `traceroute X.X.X.X` (ping = reachable, traceroute = path)",
      "back": "Sub-Q \"verify connectivity end-to-end\" \u2014 commands?",
      "tags": "flashcards/ccna-show-command-reflexes"
    },
    {
      "front": "Sub-Q \"verify application port open\" \u2014 command?",
      "back": "`telnet X.X.X.X <port>` from device (or open session test)",
      "tags": "flashcards/ccna-show-command-reflexes"
    },
    {
      "front": "`telnet X.X.X.X <port>` from device (or open session test)",
      "back": "Sub-Q \"verify application port open\" \u2014 command?",
      "tags": "flashcards/ccna-show-command-reflexes"
    },
    {
      "front": "Sub-Q \"is the static route preferred over OSPF?\"",
      "back": "`show ip route X.X.X.X` \u2014 if static AD (1) < OSPF AD (110), static wins. Output shows AD in brackets `[1/0]`.",
      "tags": "flashcards/ccna-show-command-reflexes"
    },
    {
      "front": "`show ip route X.X.X.X` \u2014 if static AD (1) < OSPF AD (110), static wins. Output shows AD in brackets `[1/0]`.",
      "back": "Sub-Q \"is the static route preferred over OSPF?\"",
      "tags": "flashcards/ccna-show-command-reflexes"
    },
    {
      "front": "Sub-Q \"is OSPF advertising the LAN?\"",
      "back": "`show ip ospf database` on a neighbor, or `show ip route ospf` on neighbor",
      "tags": "flashcards/ccna-show-command-reflexes"
    },
    {
      "front": "`show ip ospf database` on a neighbor, or `show ip route ospf` on neighbor",
      "back": "Sub-Q \"is OSPF advertising the LAN?\"",
      "tags": "flashcards/ccna-show-command-reflexes"
    },
    {
      "front": "Sub-Q \"VLAN exists on this switch?\"",
      "back": "`show vlan brief`",
      "tags": "flashcards/ccna-show-command-reflexes"
    },
    {
      "front": "`show vlan brief`",
      "back": "Sub-Q \"VLAN exists on this switch?\"",
      "tags": "flashcards/ccna-show-command-reflexes"
    },
    {
      "front": "Sub-Q \"VLAN propagated via VTP?\"",
      "back": "`show vtp status` (revision, mode, domain)",
      "tags": "flashcards/ccna-show-command-reflexes"
    },
    {
      "front": "`show vtp status` (revision, mode, domain)",
      "back": "Sub-Q \"VLAN propagated via VTP?\"",
      "tags": "flashcards/ccna-show-command-reflexes"
    },
    {
      "front": "Sub-Q \"interface in correct mode (access/trunk)?\"",
      "back": "`show interfaces gX/Y switchport`",
      "tags": "flashcards/ccna-show-command-reflexes"
    },
    {
      "front": "`show interfaces gX/Y switchport`",
      "back": "Sub-Q \"interface in correct mode (access/trunk)?\"",
      "tags": "flashcards/ccna-show-command-reflexes"
    },
    {
      "front": "Sub-Q \"verify NAT inside/outside designation?\"",
      "back": "`show ip nat statistics` (lists inside + outside interfaces) or `show running-config interface`",
      "tags": "flashcards/ccna-show-command-reflexes"
    },
    {
      "front": "`show ip nat statistics` (lists inside + outside interfaces) or `show running-config interface`",
      "back": "Sub-Q \"verify NAT inside/outside designation?\"",
      "tags": "flashcards/ccna-show-command-reflexes"
    },
    {
      "front": "Sub-Q \"verify DHCP relay configured?\"",
      "back": "`show running-config interface` \u2014 look for `ip helper-address X.X.X.X`",
      "tags": "flashcards/ccna-show-command-reflexes"
    },
    {
      "front": "`show running-config interface` \u2014 look for `ip helper-address X.X.X.X`",
      "back": "Sub-Q \"verify DHCP relay configured?\"",
      "tags": "flashcards/ccna-show-command-reflexes"
    },
    {
      "front": "Sub-Q \"is the trunk allowing VLAN 30?\"",
      "back": "`show interfaces trunk` \u2014 column \"Vlans allowed on trunk\"",
      "tags": "flashcards/ccna-show-command-reflexes"
    },
    {
      "front": "`show interfaces trunk` \u2014 column \"Vlans allowed on trunk\"",
      "back": "Sub-Q \"is the trunk allowing VLAN 30?\"",
      "tags": "flashcards/ccna-show-command-reflexes"
    },
    {
      "front": "Sub-Q \"port-channel members + load balance?\"",
      "back": "`show etherchannel summary` + `show etherchannel load-balance`",
      "tags": "flashcards/ccna-show-command-reflexes"
    },
    {
      "front": "`show etherchannel summary` + `show etherchannel load-balance`",
      "back": "Sub-Q \"port-channel members + load balance?\"",
      "tags": "flashcards/ccna-show-command-reflexes"
    },
    {
      "front": "Sub-Q \"what's the OSPF cost on Gi0/0?\"",
      "back": "`show ip ospf interface gi0/0` \u2014 line \"Cost: X\"",
      "tags": "flashcards/ccna-show-command-reflexes"
    },
    {
      "front": "`show ip ospf interface gi0/0` \u2014 line \"Cost: X\"",
      "back": "Sub-Q \"what's the OSPF cost on Gi0/0?\"",
      "tags": "flashcards/ccna-show-command-reflexes"
    },
    {
      "front": "Mental drill \u2014 every sim sub-question maps to which step?",
      "back": "1) Identify what's being checked (interface? routing? L2? service?) \u2192 2) Pick the show command that answers it \u2192 3) Run + verify \u2192 4) Tick box",
      "tags": "flashcards/ccna-show-command-reflexes"
    },
    {
      "front": "1) Identify what's being checked (interface? routing? L2? service?) \u2192 2) Pick the show command that answers it \u2192 3) Run + verify \u2192 4) Tick box",
      "back": "Mental drill \u2014 every sim sub-question maps to which step?",
      "tags": "flashcards/ccna-show-command-reflexes"
    },
    {
      "front": "Show-piping shortcut \u2014 filter long output?",
      "back": "`show run | section ospf` (named section) or `show run | include hostname` (line match) or `show run | begin interface Gi0/0` (start at)",
      "tags": "flashcards/ccna-show-command-reflexes"
    },
    {
      "front": "`show run | section ospf` (named section) or `show run | include hostname` (line match) or `show run | begin interface Gi0/0` (start at)",
      "back": "Show-piping shortcut \u2014 filter long output?",
      "tags": "flashcards/ccna-show-command-reflexes"
    },
    {
      "front": "`do` shortcut \u2014 what does it allow?",
      "back": "Run privileged exec commands (`show`) from inside any config mode without `end`/`exit`. Example: `R1(config-if)#do show ip route`",
      "tags": "flashcards/ccna-show-command-reflexes"
    },
    {
      "front": "Run privileged exec commands (`show`) from inside any config mode without `end`/`exit`. Example: `R1(config-if)#do show ip route`",
      "back": "`do` shortcut \u2014 what does it allow?",
      "tags": "flashcards/ccna-show-command-reflexes"
    }
  ]
}