{
  "questions": [
    {
      "id": "gloss-3.4-q1",
      "domain": "3",
      "topic": "3.4",
      "question": "What is the default OSPF hello interval on a broadcast network?",
      "options": ["5 seconds", "10 seconds", "30 seconds", "40 seconds"],
      "correctIndex": 1,
      "explanation": "OSPF sends hellos every 10 seconds on broadcast and point-to-point networks; dead interval is 4x = 40 seconds."
    },
    {
      "id": "gloss-3.4-q2",
      "domain": "3",
      "topic": "3.4",
      "question": "What is the correct order of OSPF neighbor states?",
      "options": ["Down → Init → 2-Way → ExStart → Exchange → Loading → Full", "Down → Init → ExStart → 2-Way → Loading → Exchange → Full", "Init → Down → 2-Way → Exchange → ExStart → Loading → Full", "Down → 2-Way → Init → ExStart → Loading → Exchange → Full"],
      "correctIndex": 0,
      "explanation": "The OSPF neighbor state progression is Down → Init → 2-Way → ExStart → Exchange → Loading → Full. DR/BDR is elected at 2-Way; LSDBs sync during Exchange and Loading."
    },
    {
      "id": "gloss-3.4-q3",
      "domain": "3",
      "topic": "3.4",
      "question": "Which OSPF LSA type is generated by every OSPF router to describe its interfaces?",
      "options": ["Type 1 (Router LSA)", "Type 2 (Network LSA)", "Type 3 (Summary LSA)", "Type 5 (AS-External LSA)"],
      "correctIndex": 0,
      "explanation": "Type 1 Router LSAs are generated by every OSPF router and list that router's OSPF-activated interfaces and networks."
    },
    {
      "id": "gloss-3.4-q4",
      "domain": "3",
      "topic": "3.4",
      "question": "Which OSPF LSA type is generated only by the DR on a multi-access network?",
      "options": ["Type 1 (Router LSA)", "Type 2 (Network LSA)", "Type 4 (ASBR Summary LSA)", "Type 5 (AS-External LSA)"],
      "correctIndex": 1,
      "explanation": "The DR generates Type 2 Network LSAs on multi-access networks, listing all routers attached to the segment."
    },
    {
      "id": "gloss-3.4-q5",
      "domain": "3",
      "topic": "3.4",
      "question": "An ASBR advertises a default route into OSPF. Which LSA type carries this?",
      "options": ["Type 1 (Router LSA)", "Type 2 (Network LSA)", "Type 3 (Summary LSA)", "Type 5 (AS-External LSA)"],
      "correctIndex": 3,
      "explanation": "Type 5 AS-External LSAs are generated by ASBRs to advertise external routes (routes outside the OSPF domain) such as a default route injected via default-information originate."
    },
    {
      "id": "gloss-3.4-q6",
      "domain": "3",
      "topic": "3.4",
      "question": "What is the OSPF cost formula?",
      "options": ["Bandwidth × delay", "Reference bandwidth ÷ interface bandwidth", "Interface bandwidth ÷ reference bandwidth", "100,000,000 ÷ delay"],
      "correctIndex": 1,
      "explanation": "OSPF cost = reference bandwidth ÷ interface bandwidth. Default reference bandwidth is 100 Mbps. Values less than 1 round up to 1."
    },
    {
      "id": "gloss-3.4-q7",
      "domain": "3",
      "topic": "3.4",
      "question": "Why is it recommended to raise the OSPF reference bandwidth from the default?",
      "options": ["To reduce CPU load on routers", "Because the default of 100 Mbps makes FastEth, GigE, and 10GigE all cost 1 — hiding faster-link preference", "To enable authentication", "To support IPv6"],
      "correctIndex": 1,
      "explanation": "With the default 100 Mbps reference, any link 100 Mbps or faster has cost 1 — the router can't distinguish GigE from 10GigE. Raising it (e.g., `auto-cost reference-bandwidth 100000`) differentiates them."
    },
    {
      "id": "gloss-3.4-q8",
      "domain": "3",
      "topic": "3.4",
      "question": "In DR/BDR election, what is the default OSPF interface priority, and what value means the router can never become DR?",
      "options": ["Default 0, never-DR is 1", "Default 1, never-DR is 0", "Default 100, never-DR is 255", "Default 255, never-DR is 0"],
      "correctIndex": 1,
      "explanation": "Default OSPF priority is 1. Setting it to 0 means the router will never become DR or BDR. Max is 255 (highest priority wins)."
    },
    {
      "id": "gloss-3.4-q9",
      "domain": "3",
      "topic": "3.4",
      "question": "If OSPF priority is tied during DR election, what breaks the tie?",
      "options": ["Lowest router ID", "Highest router ID", "Highest loopback", "First to boot"],
      "correctIndex": 1,
      "explanation": "On a priority tie, the highest router ID wins the DR election. DR/BDR is non-preemptive — once elected, a new router with a higher RID won't displace the current DR."
    },
    {
      "id": "gloss-3.4-q10",
      "domain": "3",
      "topic": "3.4",
      "question": "What multicast address does OSPF use for all OSPF routers?",
      "options": ["224.0.0.1", "224.0.0.5", "224.0.0.6", "224.0.0.9"],
      "correctIndex": 1,
      "explanation": "All-OSPF-routers multicast is 224.0.0.5. 224.0.0.6 is all-DR/BDR routers. OSPF uses IP protocol number 89."
    },
    {
      "id": "gloss-3.4-q11",
      "domain": "3",
      "topic": "3.4",
      "question": "What is the router ID selection priority in OSPF?",
      "options": ["Highest physical interface IP → highest loopback IP → manual router-id", "Manual router-id → highest loopback IP → highest physical interface IP", "Lowest loopback IP → manual router-id → highest physical interface IP", "First configured interface IP"],
      "correctIndex": 1,
      "explanation": "OSPF selects the RID using: manual `router-id` command first, then highest loopback IP, then highest active physical interface IP. Manual is always preferred."
    },
    {
      "id": "gloss-3.4-q12",
      "domain": "3",
      "topic": "3.4",
      "question": "Which OSPF neighbor requirement, if mismatched, will cause neighbors to stall in the ExStart state?",
      "options": ["Hello interval", "Area ID", "MTU", "Authentication"],
      "correctIndex": 2,
      "explanation": "Mismatched MTU causes OSPF neighbors to get stuck in ExStart. Hello/dead mismatches prevent neighbors from forming at all; area and authentication mismatches prevent adjacency earlier."
    },
    {
      "id": "gloss-3.4-q13",
      "domain": "3",
      "topic": "3.4",
      "question": "On a broadcast segment, what state do two DROthers remain in with each other?",
      "options": ["Full", "Loading", "2-Way", "Down"],
      "correctIndex": 2,
      "explanation": "DROthers stay in 2-Way state with other DROthers — they don't form full adjacencies. Each DROther forms Full adjacency only with the DR and BDR."
    },
    {
      "id": "gloss-3.4-q14",
      "domain": "3",
      "topic": "3.4",
      "question": "What happens in OSPF's Exchange state?",
      "options": ["Hellos are exchanged to discover neighbors", "DBDs (Database Descriptions) are exchanged to describe each LSDB", "LSUs carrying actual LSAs are transmitted", "The SPF algorithm runs"],
      "correctIndex": 1,
      "explanation": "In Exchange state, neighbors exchange DBD packets summarizing their LSDBs. Loading state then uses LSR/LSU/LSAck to request and deliver missing LSAs."
    },
    {
      "id": "gloss-3.4-q15",
      "domain": "3",
      "topic": "3.4",
      "question": "What is the default OSPF dead interval on a non-broadcast network?",
      "options": ["40 seconds", "60 seconds", "120 seconds", "180 seconds"],
      "correctIndex": 2,
      "explanation": "Non-broadcast (e.g., Frame Relay) defaults are Hello 30 s, Dead 120 s — 4x the hello timer. Broadcast and point-to-point use Hello 10 s, Dead 40 s."
    }
  ]
}
