{
  "questions": [
    {
      "id": "gloss-4.4-q1",
      "domain": "4",
      "topic": "4.4",
      "question": "Which SNMP version is currently preferred because it supports strong authentication and encryption?",
      "options": [
        "SNMPv1",
        "SNMPv2c",
        "SNMPv3",
        "SNMPv4"
      ],
      "correctIndex": 2,
      "explanation": "SNMPv3 adds strong authentication and encryption, making it the preferred version. v1 and v2c use plain-text community strings."
    },
    {
      "id": "gloss-4.4-q2",
      "domain": "4",
      "topic": "4.4",
      "question": "Which UDP ports does SNMP use?",
      "options": [
        "Agents on 161, Managers on 162",
        "Agents on 162, Managers on 161",
        "Both on 161",
        "Both on 514"
      ],
      "correctIndex": 0,
      "explanation": "SNMP Agents listen on UDP 161 (for Get/Set). SNMP Managers listen on UDP 162 (for Traps and Informs)."
    },
    {
      "id": "gloss-4.4-q3",
      "domain": "4",
      "topic": "4.4",
      "question": "What is a MIB in SNMP?",
      "options": [
        "A log of SNMP transactions",
        "A hierarchical structure of variables managed on each device",
        "A management image booted on the NMS",
        "A backup of the SNMP community string"
      ],
      "correctIndex": 1,
      "explanation": "The Management Information Base (MIB) is the hierarchical tree of variables (identified by OIDs) that an SNMP agent exposes."
    },
    {
      "id": "gloss-4.4-q4",
      "domain": "4",
      "topic": "4.4",
      "question": "Which statement about SNMP Traps is correct?",
      "options": [
        "They are sent by the NMS to the agent and are acknowledged",
        "They are unsolicited notifications from agent to NMS and are NOT acknowledged",
        "They are unsolicited notifications that are always acknowledged with a Response",
        "They are Get requests issued by the agent"
      ],
      "correctIndex": 1,
      "explanation": "Traps are unsolicited agent-to-NMS notifications with no acknowledgment — that makes them unreliable. Informs are the acknowledged variant."
    },
    {
      "id": "gloss-4.4-q5",
      "domain": "4",
      "topic": "4.4",
      "question": "Which SNMP message is like a Trap but is acknowledged by the manager?",
      "options": [
        "Get",
        "GetNext",
        "Inform",
        "Set"
      ],
      "correctIndex": 2,
      "explanation": "Informs are agent-to-NMS notifications that receive a Response, making them reliable (unlike Traps)."
    },
    {
      "id": "gloss-4.4-q6",
      "domain": "4",
      "topic": "4.4",
      "question": "Which SNMPv2+ operation efficiently retrieves a large block of OIDs at once?",
      "options": [
        "Get",
        "GetNext",
        "GetBulk",
        "Set"
      ],
      "correctIndex": 2,
      "explanation": "GetBulk was introduced in SNMPv2 as an efficient alternative to repeated GetNext calls."
    },
    {
      "id": "gloss-4.4-q7",
      "domain": "4",
      "topic": "4.4",
      "question": "What are the default community strings historically used with SNMPv1/v2c?",
      "options": [
        "'public' (RO) and 'private' (RW)",
        "'cisco' (RO) and 'secret' (RW)",
        "'admin' (RO) and 'admin' (RW)",
        "'read' (RO) and 'write' (RW)"
      ],
      "correctIndex": 0,
      "explanation": "The well-known defaults are 'public' (read-only) and 'private' (read-write). Leaving these defaults is a security risk."
    },
    {
      "id": "gloss-4.4-q8",
      "domain": "4",
      "topic": "4.4",
      "question": "What does OID stand for in SNMP?",
      "options": [
        "Open Interface Descriptor",
        "Object Identifier",
        "Operational ID",
        "Object Information Database"
      ],
      "correctIndex": 1,
      "explanation": "OID = Object Identifier — the unique identifier for each variable in the MIB (e.g., sysName for hostname)."
    },
    {
      "id": "gloss-4.4-q9",
      "domain": "4",
      "topic": "4.4",
      "question": "Which component runs on the managed device and communicates with the SNMP manager?",
      "options": [
        "SNMP Manager",
        "SNMP Application",
        "SNMP Agent",
        "NMS"
      ],
      "correctIndex": 2,
      "explanation": "The SNMP Agent is the software on the managed device (router/switch) that talks to the SNMP Manager running on the NMS."
    },
    {
      "id": "gloss-4.4-q10",
      "domain": "4",
      "topic": "4.4",
      "question": "Which command defines an SNMP community string with read-only access?",
      "options": [
        "snmp-server community public RO",
        "snmp-server community public RW",
        "snmp-server host public RO",
        "snmp-server enable traps community public"
      ],
      "correctIndex": 0,
      "explanation": "'snmp-server community <string> RO' configures a read-only community string for SNMP access."
    },
    {
      "id": "gloss-4.4-q11",
      "domain": "4",
      "topic": "4.4",
      "question": "To which SNMP message class do Get, GetNext, and GetBulk belong?",
      "options": [
        "Write class",
        "Read class",
        "Notification class",
        "Response class"
      ],
      "correctIndex": 1,
      "explanation": "Get, GetNext, and GetBulk all belong to the read class. Set is the write class; Trap/Inform are notification class."
    },
    {
      "id": "gloss-4.4-q12",
      "domain": "4",
      "topic": "4.4",
      "question": "What is the NMS in SNMP?",
      "options": [
        "A managed network device such as a router or switch",
        "The Network Management Station running the SNMP Manager software",
        "The Network Monitoring Signal used to detect agents",
        "A command-line tool for reading the MIB"
      ],
      "correctIndex": 1,
      "explanation": "NMS = Network Management Station (or System) — the server running SNMP Manager/application software (e.g., SolarWinds)."
    }
  ]
}
